MANIFEST.in
README.txt
setup.cfg
setup.py
rc/__init__.py
rc.docs.egg-info/PKG-INFO
rc.docs.egg-info/SOURCES.txt
rc.docs.egg-info/dependency_links.txt
rc.docs.egg-info/entry_points.txt
rc.docs.egg-info/namespace_packages.txt
rc.docs.egg-info/not-zip-safe
rc.docs.egg-info/paster_plugins.txt
rc.docs.egg-info/requires.txt
rc.docs.egg-info/top_level.txt
rc/docs/README.txt
rc/docs/__init__.py
rc/docs/config.py
rc/docs/configure.zcml
rc/docs/setuphandlers.py
rc/docs/browser/__init__.py
rc/docs/browser/configure.zcml
rc/docs/browser/fachartikelview.pt
rc/docs/browser/fachartikelview.py
rc/docs/browser/qtview.pt
rc/docs/browser/qtview.py
rc/docs/browser/quellentextview.pt
rc/docs/browser/quellentextview.py
rc/docs/content/__init__.py
rc/docs/content/configure.zcml
rc/docs/content/fachartikel.py
rc/docs/content/quellentext.py
rc/docs/interfaces/__init__.py
rc/docs/interfaces/fachartikel.py
rc/docs/interfaces/quellentext.py
rc/docs/portlets/__init__.py
rc/docs/portlets/configure.zcml
rc/docs/profiles/default/catalog.xml
rc/docs/profiles/default/factorytool.xml
rc/docs/profiles/default/metadata.xml
rc/docs/profiles/default/portlets.xml
rc/docs/profiles/default/rolemap.xml
rc/docs/profiles/default/rolemap.xml.old
rc/docs/profiles/default/types.xml
rc/docs/profiles/default/workflows.xml
rc/docs/profiles/default/types/Fachartikel.xml
rc/docs/profiles/default/types/Quellentext.xml
rc/docs/profiles/default/workflows/redaktion_workflow/definition.xml
rc/docs/tests/__init__.py
rc/docs/tests/base.py
rc/docs/tests/test_doctest.py