Metadata-Version: 1.0
Name: rc.docs
Version: 1.21
Summary: rcDocs
Home-page: http://svn.plone.org/svn/plone/plone.example
Author: INF
Author-email: inf@uni-trier.de
License: GPL
Keywords: sfb rcdocs
Platform: UNKNOWN
Classifier: Framework :: Plone
Classifier: Intended Audience :: Developers
Classifier: License :: OSI Approved :: GNU General Public License (GPL)
